spacelift/__init__.py
spacelift/main.py
spacelift/mock_spacelift.py
spacelift-1.1.2.dist-info/LICENSE
spacelift-1.1.2.dist-info/METADATA
spacelift-1.1.2.dist-info/WHEEL
spacelift-1.1.2.dist-info/RECORD
